OpenFisca_France-18.8.2.data/data/share/openfisca/openfisca-france/CHANGELOG.md
OpenFisca_France-18.8.2.data/data/share/openfisca/openfisca-france/LICENSE.AGPL.txt
OpenFisca_France-18.8.2.data/data/share/openfisca/openfisca-france/README.md
OpenFisca_France-18.8.2.dist-info/DESCRIPTION.rst
OpenFisca_France-18.8.2.dist-info/METADATA
OpenFisca_France-18.8.2.dist-info/RECORD
OpenFisca_France-18.8.2.dist-info/WHEEL
OpenFisca_France-18.8.2.dist-info/metadata.json
OpenFisca_France-18.8.2.dist-info/top_level.txt
openfisca_france/__init__.py
openfisca_france/entities.py
openfisca_france/france_taxbenefitsystem.py
openfisca_france/scenarios.py
openfisca_france/assets/__init__.py
openfisca_france/assets/holidays.py
openfisca_france/assets/apl/20110914_zonage.csv
openfisca_france/assets/apl/README.md
openfisca_france/assets/apl/commune_depcom_by_subcommune_depcom.json
openfisca_france/assets/apl/extract_subcommunes.py
openfisca_france/assets/versement_transport/taux.json
openfisca_france/conf/__init__.py
openfisca_france/conf/cache_blacklist.py
openfisca_france/decompositions/__init__.py
openfisca_france/decompositions/decomp.xml
openfisca_france/decompositions/decomp_contrib.xml
openfisca_france/decompositions/decomp_prestations.xml
openfisca_france/decompositions/decompositions-multiples.xml
openfisca_france/decompositions/fiche_de_paie_decomposition.xml
openfisca_france/model/__init__.py
openfisca_france/model/base.py
openfisca_france/model/mesures.py
openfisca_france/model/caracteristiques_socio_demographiques/__init__.py
openfisca_france/model/caracteristiques_socio_demographiques/demographie.py
openfisca_france/model/caracteristiques_socio_demographiques/logement.py
openfisca_france/model/consommation/__init__.py
openfisca_france/model/patrimoine/__init__.py
openfisca_france/model/prelevements_obligatoires/__init__.py
openfisca_france/model/prelevements_obligatoires/isf.py
openfisca_france/model/prelevements_obligatoires/taxe_habitation.py
openfisca_france/model/prelevements_obligatoires/impot_revenu/__init__.py
openfisca_france/model/prelevements_obligatoires/impot_revenu/charges_deductibles.py
openfisca_france/model/prelevements_obligatoires/impot_revenu/credits_impot.py
