Metadata-Version: 2.0
Name: OpenFisca-France
Version: 18.8.2
Summary: French tax and benefit system for OpenFisca
Home-page: https://github.com/openfisca/openfisca-france
Author: OpenFisca Team
Author-email: contact@openfisca.fr
License: http://www.fsf.org/licensing/licenses/agpl-3.0.html
Keywords: benefit france microsimulation social tax
Platform: UNKNOWN
Classifier: Development Status :: 2 - Pre-Alpha
Classifier: License :: OSI Approved :: GNU Affero General Public License v3
Classifier: Operating System :: POSIX
Classifier: Programming Language :: Python
Classifier: Topic :: Scientific/Engineering :: Information Analysis
Requires-Dist: Biryani[datetimeconv] (>=0.10.4)
Requires-Dist: OpenFisca-Core (<17.0,>=15.0.0)
Requires-Dist: PyYAML (>=3.10)
Requires-Dist: numpy (>=1.11,<1.13)
Requires-Dist: requests (>=2.8)
Provides-Extra: api
Requires-Dist: OpenFisca-Web-API (>=6.1.0,<7.0); extra == 'api'
Provides-Extra: baremes_ipp
Requires-Dist: lxml (>=3.8.0,<4.0); extra == 'baremes_ipp'
Requires-Dist: xlrd (>=1.0.0); extra == 'baremes_ipp'
Provides-Extra: de_net_a_brut
Requires-Dist: scipy (>=0.17); extra == 'de_net_a_brut'
Provides-Extra: inversion_revenus
Requires-Dist: scipy (>=0.17); extra == 'inversion_revenus'
Provides-Extra: taxipp
Requires-Dist: pandas (>=0.13); extra == 'taxipp'
Provides-Extra: test
Requires-Dist: flake8; extra == 'test'
Requires-Dist: nose; extra == 'test'
Requires-Dist: scipy (>=0.17); extra == 'test'
